MANIFEST.in
README.rst
setup.cfg
setup.py
tw2/__init__.py
tw2.ace.egg-info/PKG-INFO
tw2.ace.egg-info/SOURCES.txt
tw2.ace.egg-info/dependency_links.txt
tw2.ace.egg-info/entry_points.txt
tw2.ace.egg-info/namespace_packages.txt
tw2.ace.egg-info/not-zip-safe
tw2.ace.egg-info/paster_plugins.txt
tw2.ace.egg-info/requires.txt
tw2.ace.egg-info/top_level.txt
tw2/ace/__init__.py
tw2/ace/samples.py
tw2/ace/widgets.py
tw2/ace/static/tw2_ace.js
tw2/ace/static/ace/ace.js
tw2/ace/static/ace/ext-static_highlight.js
tw2/ace/static/ace/ext-textarea.js
tw2/ace/static/ace/keybinding-emacs.js
tw2/ace/static/ace/keybinding-vim.js
tw2/ace/static/ace/mode-asciidoc.js
tw2/ace/static/ace/mode-c9search.js
tw2/ace/static/ace/mode-c_cpp.js
tw2/ace/static/ace/mode-clojure.js
tw2/ace/static/ace/mode-coffee.js
tw2/ace/static/ace/mode-coldfusion.js
tw2/ace/static/ace/mode-csharp.js
tw2/ace/static/ace/mode-css.js
tw2/ace/static/ace/mode-diff.js
tw2/ace/static/ace/mode-glsl.js
tw2/ace/static/ace/mode-golang.js
tw2/ace/static/ace/mode-groovy.js
tw2/ace/static/ace/mode-haskell.js
tw2/ace/static/ace/mode-haxe.js
tw2/ace/static/ace/mode-html.js
tw2/ace/static/ace/mode-jade.js
tw2/ace/static/ace/mode-java.js
tw2/ace/static/ace/mode-javascript.js
tw2/ace/static/ace/mode-json.js
tw2/ace/static/ace/mode-jsp.js
tw2/ace/static/ace/mode-jsx.js
tw2/ace/static/ace/mode-latex.js
tw2/ace/static/ace/mode-less.js
tw2/ace/static/ace/mode-liquid.js
tw2/ace/static/ace/mode-lua.js
tw2/ace/static/ace/mode-luapage.js
tw2/ace/static/ace/mode-markdown.js
tw2/ace/static/ace/mode-ocaml.js
tw2/ace/static/ace/mode-perl.js
tw2/ace/static/ace/mode-pgsql.js
tw2/ace/static/ace/mode-php.js
tw2/ace/static/ace/mode-powershell.js
tw2/ace/static/ace/mode-prolog.js
tw2/ace/static/ace/mode-python.js
tw2/ace/static/ace/mode-ruby.js
tw2/ace/static/ace/mode-scad.js
tw2/ace/static/ace/mode-scala.js
tw2/ace/static/ace/mode-scss.js
tw2/ace/static/ace/mode-sh.js
tw2/ace/static/ace/mode-sql.js
tw2/ace/static/ace/mode-svg.js
tw2/ace/static/ace/mode-tcl.js
tw2/ace/static/ace/mode-text.js
tw2/ace/static/ace/mode-textile.js
tw2/ace/static/ace/mode-typescript.js
tw2/ace/static/ace/mode-xml.js
tw2/ace/static/ace/mode-xquery.js
tw2/ace/static/ace/mode-yaml.js
tw2/ace/static/ace/theme-ambiance.js
tw2/ace/static/ace/theme-chrome.js
